{
  "admin": {
    "displayName": "Administrator",
    "levels": ["general"],
    "access": {
      "receiptControl": true,
      "specs": true,
      "itemRead": true,
      "itemWrite": true,
      "itemEdit": true,
      "itemRepair": true,
      "finalInspection": true,
      "finished": true
    }
  },
  "lead": {
    "displayName": "Lead Engineer",
    "levels": ["general"],
    "access": {
      "receiptControl": false,
      "specs": true,
      "itemRead": true,
      "itemWrite": false,
      "itemEdit": false,
      "itemRepair": true,
      "finalInspection": false,
      "finished": true
    }
  },
  "supervisor": {
    "displayName": "Supervisor",
    "levels": ["general"],
    "access": {
      "receiptControl": false,
      "specs": false,
      "itemRead": true,
      "itemWrite": true,
      "itemEdit": true,
      "itemRepair": true,
      "finalInspection": true,
      "finished": true
    }
  },
  "operator": {
    "displayName": "Operator",
    "levels": ["general"],
    "access": {
      "receiptControl": false,
      "specs": false,
      "itemRead": true,
      "itemWrite": true,
      "itemEdit": false,
      "itemRepair": false,
      "finalInspection": true,
      "finished": true
    }
  },
  "quality": {
    "displayName": "Quality Control",
    "levels": ["general"],
    "access": {
      "receiptControl": false,
      "specs": false,
      "itemRead": true,
      "itemWrite": false,
      "itemEdit": true,
      "itemRepair": true,
      "finalInspection": true,
      "finished": true
    }
  },
  "offsite": {
    "displayName": "Offsite Responsible",
    "levels": ["project"],
    "access": {
      "receiptControl": false,
      "specs": false,
      "itemRead": true,
      "itemWrite": true,
      "itemEdit": false,
      "itemRepair": false,
      "finalInspection": true,
      "finished": true
    }
  },
  "spectator": {
    "displayName": "Spectator",
    "levels": ["general"],
    "access": {
      "receiptControl": false,
      "specs": false,
      "itemRead": true,
      "itemWrite": false,
      "itemEdit": false,
      "itemRepair": false,
      "finalInspection": false,
      "finished": true
    }
  }
}
